{
    "tags": [],
    "description": "",
    "objects": [
        {
            "id": 1164145751,
            "classId": 11380051,
            "description": "",
            "geometryType": "polygon",
            "labelerLogin": "GhazalehHITL",
            "createdAt": "2023-01-18T10:49:38.474Z",
            "updatedAt": "2023-04-04T16:47:20.620Z",
            "tags": [],
            "classTitle": "Missing part",
            "points": {
                "exterior": [
                    [
                        483.0,
                        85.0
                    ],
                    [
                        495.0,
                        97.0
                    ],
                    [
                        503.0,
                        88.0
                    ],
                    [
                        524.0,
                        89.0
                    ],
                    [
                        529.0,
                        98.0
                    ],
                    [
                        534.0,
                        106.0
                    ],
                    [
                        517.0,
                        109.0
                    ],
                    [
                        506.0,
                        108.0
                    ],
                    [
                        497.0,
                        107.0
                    ],
                    [
                        491.0,
                        109.0
                    ],
                    [
                        487.0,
                        109.0
                    ],
                    [
                        484.0,
                        97.0
                    ]
                ],
                "interior": []
            }
        },
        {
            "id": 1164145756,
            "classId": 11380052,
            "description": "",
            "geometryType": "polygon",
            "labelerLogin": "GhazalehHITL",
            "createdAt": "2023-01-18T10:49:38.474Z",
            "updatedAt": "2023-04-04T16:47:20.620Z",
            "tags": [],
            "classTitle": "Broken part",
            "points": {
                "exterior": [
                    [
                        433.0,
                        39.0
                    ],
                    [
                        443.0,
                        45.0
                    ],
                    [
                        459.0,
                        53.0
                    ],
                    [
                        473.0,
                        67.0
                    ],
                    [
                        487.0,
                        87.0
                    ],
                    [
                        496.0,
                        111.0
                    ],
                    [
                        504.0,
                        128.0
                    ],
                    [
                        507.0,
                        138.0
                    ],
                    [
                        509.0,
                        145.0
                    ],
                    [
                        502.0,
                        160.0
                    ],
                    [
                        498.0,
                        175.0
                    ],
                    [
                        491.0,
                        195.0
                    ],
                    [
                        464.0,
                        219.0
                    ],
                    [
                        449.0,
                        229.0
                    ],
                    [
                        446.0,
                        216.0
                    ],
                    [
                        449.0,
                        204.0
                    ],
                    [
                        453.0,
                        189.0
                    ],
                    [
                        457.0,
                        168.0
                    ],
                    [
                        457.0,
                        154.0
                    ],
                    [
                        456.0,
                        133.0
                    ],
                    [
                        450.0,
                        115.0
                    ],
                    [
                        444.0,
                        108.0
                    ],
                    [
                        431.0,
                        63.0
                    ],
                    [
                        420.0,
                        36.0
                    ]
                ],
                "interior": []
            }
        },
        {
            "id": 1164145755,
            "classId": 11380055,
            "description": "",
            "geometryType": "polygon",
            "labelerLogin": "GhazalehHITL",
            "createdAt": "2023-01-18T10:49:38.474Z",
            "updatedAt": "2023-04-04T16:47:20.620Z",
            "tags": [],
            "classTitle": "Dent",
            "points": {
                "exterior": [
                    [
                        477.0,
                        124.0
                    ],
                    [
                        482.0,
                        131.0
                    ],
                    [
                        484.0,
                        139.0
                    ],
                    [
                        482.0,
                        150.0
                    ],
                    [
                        479.0,
                        157.0
                    ],
                    [
                        478.0,
                        162.0
                    ],
                    [
                        476.0,
                        168.0
                    ],
                    [
                        476.0,
                        173.0
                    ],
                    [
                        469.0,
                        184.0
                    ],
                    [
                        464.0,
                        180.0
                    ],
                    [
                        467.0,
                        169.0
                    ],
                    [
                        467.0,
                        154.0
                    ],
                    [
                        467.0,
                        142.0
                    ],
                    [
                        466.0,
                        131.0
                    ],
                    [
                        465.0,
                        127.0
                    ],
                    [
                        463.0,
                        121.0
                    ],
                    [
                        467.0,
                        119.0
                    ],
                    [
                        471.0,
                        120.0
                    ],
                    [
                        474.0,
                        121.0
                    ]
                ],
                "interior": []
            }
        },
        {
            "id": 1164145757,
            "classId": 11380055,
            "description": "",
            "geometryType": "polygon",
            "labelerLogin": "GhazalehHITL",
            "createdAt": "2023-01-18T10:49:38.474Z",
            "updatedAt": "2023-04-04T16:47:20.620Z",
            "tags": [],
            "classTitle": "Dent",
            "points": {
                "exterior": [
                    [
                        489.0,
                        147.0
                    ],
                    [
                        492.0,
                        154.0
                    ],
                    [
                        496.0,
                        159.0
                    ],
                    [
                        494.0,
                        166.0
                    ],
                    [
                        490.0,
                        173.0
                    ],
                    [
                        488.0,
                        181.0
                    ],
                    [
                        486.0,
                        183.0
                    ],
                    [
                        484.0,
                        181.0
                    ],
                    [
                        484.0,
                        175.0
                    ],
                    [
                        486.0,
                        168.0
                    ],
                    [
                        487.0,
                        159.0
                    ],
                    [
                        487.0,
                        152.0
                    ],
                    [
                        487.0,
                        149.0
                    ]
                ],
                "interior": []
            }
        },
        {
            "id": 1164145724,
            "classId": 11380055,
            "description": "",
            "geometryType": "polygon",
            "labelerLogin": "GhazalehHITL",
            "createdAt": "2023-01-18T10:49:38.474Z",
            "updatedAt": "2023-04-04T16:47:20.620Z",
            "tags": [],
            "classTitle": "Dent",
            "points": {
                "exterior": [
                    [
                        504.0,
                        134.0
                    ],
                    [
                        508.0,
                        138.0
                    ],
                    [
                        511.0,
                        142.0
                    ],
                    [
                        507.0,
                        151.0
                    ],
                    [
                        504.0,
                        159.0
                    ],
                    [
                        501.0,
                        166.0
                    ],
                    [
                        499.0,
                        170.0
                    ],
                    [
                        498.0,
                        169.0
                    ],
                    [
                        500.0,
                        156.0
                    ],
                    [
                        500.0,
                        143.0
                    ],
                    [
                        501.0,
                        136.0
                    ],
                    [
                        501.0,
                        134.0
                    ]
                ],
                "interior": []
            }
        },
        {
            "id": 1164145745,
            "classId": 11380055,
            "description": "",
            "geometryType": "polygon",
            "labelerLogin": "GhazalehHITL",
            "createdAt": "2023-01-18T10:49:38.474Z",
            "updatedAt": "2023-04-04T16:47:20.620Z",
            "tags": [],
            "classTitle": "Dent",
            "points": {
                "exterior": [
                    [
                        411.0,
                        114.0
                    ],
                    [
                        418.0,
                        126.0
                    ],
                    [
                        423.0,
                        135.0
                    ],
                    [
                        427.0,
                        144.0
                    ],
                    [
                        426.0,
                        152.0
                    ],
                    [
                        419.0,
                        160.0
                    ],
                    [
                        414.0,
                        161.0
                    ],
                    [
                        416.0,
                        153.0
                    ],
                    [
                        418.0,
                        145.0
                    ],
                    [
                        414.0,
                        135.0
                    ],
                    [
                        408.0,
                        126.0
                    ],
                    [
                        407.0,
                        117.0
                    ]
                ],
                "interior": []
            }
        },
        {
            "id": 1164145753,
            "classId": 11380055,
            "description": "",
            "geometryType": "polygon",
            "labelerLogin": "GhazalehHITL",
            "createdAt": "2023-01-18T10:49:38.474Z",
            "updatedAt": "2023-04-04T16:47:20.620Z",
            "tags": [],
            "classTitle": "Dent",
            "points": {
                "exterior": [
                    [
                        386.0,
                        172.0
                    ],
                    [
                        394.0,
                        176.0
                    ],
                    [
                        395.0,
                        187.0
                    ],
                    [
                        393.0,
                        197.0
                    ],
                    [
                        386.0,
                        197.0
                    ],
                    [
                        381.0,
                        193.0
                    ],
                    [
                        377.0,
                        185.0
                    ],
                    [
                        376.0,
                        175.0
                    ],
                    [
                        377.0,
                        170.0
                    ]
                ],
                "interior": []
            }
        },
        {
            "id": 1164145746,
            "classId": 11380055,
            "description": "",
            "geometryType": "polygon",
            "labelerLogin": "GhazalehHITL",
            "createdAt": "2023-01-18T10:49:38.474Z",
            "updatedAt": "2023-04-04T16:47:20.620Z",
            "tags": [],
            "classTitle": "Dent",
            "points": {
                "exterior": [
                    [
                        508.0,
                        119.0
                    ],
                    [
                        514.0,
                        125.0
                    ],
                    [
                        517.0,
                        130.0
                    ],
                    [
                        514.0,
                        136.0
                    ],
                    [
                        511.0,
                        139.0
                    ],
                    [
                        508.0,
                        137.0
                    ],
                    [
                        504.0,
                        131.0
                    ],
                    [
                        501.0,
                        127.0
                    ],
                    [
                        501.0,
                        121.0
                    ],
                    [
                        504.0,
                        117.0
                    ]
                ],
                "interior": []
            }
        },
        {
            "id": 1164145769,
            "classId": 11380053,
            "description": "",
            "geometryType": "polygon",
            "labelerLogin": "GhazalehHITL",
            "createdAt": "2023-01-18T10:49:38.474Z",
            "updatedAt": "2023-04-04T16:47:20.620Z",
            "tags": [],
            "classTitle": "Scratch",
            "points": {
                "exterior": [
                    [
                        304.0,
                        269.0
                    ],
                    [
                        290.0,
                        271.0
                    ],
                    [
                        283.0,
                        272.0
                    ],
                    [
                        278.0,
                        272.0
                    ],
                    [
                        271.0,
                        270.0
                    ],
                    [
                        268.0,
                        272.0
                    ],
                    [
                        261.0,
                        274.0
                    ],
                    [
                        253.0,
                        277.0
                    ],
                    [
                        244.0,
                        277.0
                    ],
                    [
                        252.0,
                        280.0
                    ],
                    [
                        267.0,
                        279.0
                    ],
                    [
                        305.0,
                        274.0
                    ]
                ],
                "interior": []
            }
        },
        {
            "id": 1260824130,
            "classId": 11380051,
            "description": "",
            "geometryType": "polygon",
            "labelerLogin": "MojtabaHITL",
            "createdAt": "2023-03-21T16:02:03.579Z",
            "updatedAt": "2023-04-04T16:47:20.620Z",
            "tags": [],
            "classTitle": "Missing part",
            "points": {
                "exterior": [
                    [
                        74.0,
                        154.0
                    ],
                    [
                        118.0,
                        160.0
                    ],
                    [
                        116.0,
                        196.0
                    ],
                    [
                        71.0,
                        187.0
                    ]
                ],
                "interior": []
            }
        },
        {
            "id": 1270782421,
            "classId": 11380051,
            "description": "",
            "geometryType": "polygon",
            "labelerLogin": "MojtabaHITL",
            "createdAt": "2023-04-04T16:47:20.551Z",
            "updatedAt": "2023-04-04T16:47:24.255Z",
            "tags": [],
            "classTitle": "Missing part",
            "points": {
                "exterior": [
                    [
                        483.0,
                        140.0
                    ],
                    [
                        470.0,
                        140.0
                    ],
                    [
                        468.0,
                        130.0
                    ],
                    [
                        476.0,
                        128.0
                    ],
                    [
                        484.0,
                        131.0
                    ]
                ],
                "interior": []
            }
        }
    ],
    "size": {
        "height": 429,
        "width": 569
    }
}