{
    "tags": [],
    "description": "",
    "objects": [
        {
            "id": 1164141315,
            "classId": 11380055,
            "description": "",
            "geometryType": "polygon",
            "labelerLogin": "GhazalehHITL",
            "createdAt": "2023-01-18T10:42:17.026Z",
            "updatedAt": "2023-03-20T07:32:06.669Z",
            "tags": [],
            "classTitle": "Dent",
            "points": {
                "exterior": [
                    [
                        391.0,
                        426.0
                    ],
                    [
                        385.0,
                        460.0
                    ],
                    [
                        388.0,
                        481.0
                    ],
                    [
                        398.0,
                        500.0
                    ],
                    [
                        407.0,
                        514.0
                    ],
                    [
                        434.0,
                        516.0
                    ],
                    [
                        466.0,
                        506.0
                    ],
                    [
                        477.0,
                        486.0
                    ],
                    [
                        480.0,
                        465.0
                    ],
                    [
                        483.0,
                        442.0
                    ],
                    [
                        483.0,
                        427.0
                    ],
                    [
                        476.0,
                        415.0
                    ],
                    [
                        461.0,
                        411.0
                    ],
                    [
                        441.0,
                        414.0
                    ],
                    [
                        418.0,
                        415.0
                    ]
                ],
                "interior": []
            }
        },
        {
            "id": 1164141263,
            "classId": 11380053,
            "description": "",
            "geometryType": "polygon",
            "labelerLogin": "GhazalehHITL",
            "createdAt": "2023-01-18T10:42:17.026Z",
            "updatedAt": "2023-03-20T07:32:06.669Z",
            "tags": [],
            "classTitle": "Scratch",
            "points": {
                "exterior": [
                    [
                        401.0,
                        488.0
                    ],
                    [
                        404.0,
                        503.0
                    ],
                    [
                        411.0,
                        513.0
                    ],
                    [
                        427.0,
                        515.0
                    ],
                    [
                        439.0,
                        510.0
                    ],
                    [
                        429.0,
                        506.0
                    ],
                    [
                        414.0,
                        499.0
                    ],
                    [
                        410.0,
                        488.0
                    ],
                    [
                        408.0,
                        482.0
                    ]
                ],
                "interior": []
            }
        },
        {
            "id": 1164141272,
            "classId": 11380057,
            "description": "",
            "geometryType": "polygon",
            "labelerLogin": "GhazalehHITL",
            "createdAt": "2023-01-18T10:42:17.026Z",
            "updatedAt": "2023-03-20T07:32:06.669Z",
            "tags": [],
            "classTitle": "Paint chip",
            "points": {
                "exterior": [
                    [
                        567.0,
                        306.0
                    ],
                    [
                        580.0,
                        316.0
                    ],
                    [
                        587.0,
                        321.0
                    ],
                    [
                        601.0,
                        319.0
                    ],
                    [
                        604.0,
                        308.0
                    ],
                    [
                        592.0,
                        308.0
                    ],
                    [
                        579.0,
                        307.0
                    ],
                    [
                        561.0,
                        301.0
                    ]
                ],
                "interior": []
            }
        },
        {
            "id": 1164141406,
            "classId": 11380057,
            "description": "",
            "geometryType": "polygon",
            "labelerLogin": "GhazalehHITL",
            "createdAt": "2023-01-18T10:42:17.026Z",
            "updatedAt": "2023-03-20T07:32:06.669Z",
            "tags": [],
            "classTitle": "Paint chip",
            "points": {
                "exterior": [
                    [
                        139.0,
                        207.0
                    ],
                    [
                        148.0,
                        215.0
                    ],
                    [
                        167.0,
                        223.0
                    ],
                    [
                        188.0,
                        229.0
                    ],
                    [
                        211.0,
                        235.0
                    ],
                    [
                        208.0,
                        226.0
                    ],
                    [
                        190.0,
                        219.0
                    ],
                    [
                        168.0,
                        214.0
                    ],
                    [
                        154.0,
                        210.0
                    ]
                ],
                "interior": []
            }
        },
        {
            "id": 1164141522,
            "classId": 11380052,
            "description": "",
            "geometryType": "polygon",
            "labelerLogin": "GhazalehHITL",
            "createdAt": "2023-01-18T10:42:17.026Z",
            "updatedAt": "2023-04-03T09:33:27.931Z",
            "tags": [],
            "classTitle": "Broken part",
            "points": {
                "exterior": [
                    [
                        629.0,
                        215.0
                    ],
                    [
                        641.0,
                        235.0
                    ],
                    [
                        659.0,
                        271.0
                    ],
                    [
                        684.0,
                        316.0
                    ],
                    [
                        685.0,
                        340.0
                    ],
                    [
                        684.0,
                        372.0
                    ],
                    [
                        688.0,
                        369.0
                    ],
                    [
                        692.0,
                        342.0
                    ],
                    [
                        693.0,
                        314.0
                    ],
                    [
                        682.0,
                        292.0
                    ],
                    [
                        666.0,
                        263.0
                    ],
                    [
                        660.0,
                        247.0
                    ],
                    [
                        641.0,
                        215.0
                    ]
                ],
                "interior": []
            }
        },
        {
            "id": 1253766611,
            "classId": 11380057,
            "description": "",
            "geometryType": "polygon",
            "labelerLogin": "MojtabaHITL",
            "createdAt": "2023-03-20T07:31:40.271Z",
            "updatedAt": "2023-03-20T07:32:06.669Z",
            "tags": [],
            "classTitle": "Paint chip",
            "points": {
                "exterior": [
                    [
                        561.0,
                        296.0
                    ],
                    [
                        558.0,
                        289.0
                    ],
                    [
                        558.0,
                        285.0
                    ],
                    [
                        557.0,
                        278.0
                    ],
                    [
                        557.0,
                        270.0
                    ],
                    [
                        554.0,
                        272.0
                    ],
                    [
                        554.0,
                        280.0
                    ],
                    [
                        557.0,
                        294.0
                    ],
                    [
                        559.0,
                        296.0
                    ]
                ],
                "interior": []
            }
        },
        {
            "id": 1253766662,
            "classId": 11380057,
            "description": "",
            "geometryType": "polygon",
            "labelerLogin": "MojtabaHITL",
            "createdAt": "2023-03-20T07:32:06.574Z",
            "updatedAt": "2023-03-20T07:32:18.250Z",
            "tags": [],
            "classTitle": "Paint chip",
            "points": {
                "exterior": [
                    [
                        501.0,
                        316.0
                    ],
                    [
                        498.0,
                        313.0
                    ],
                    [
                        494.0,
                        308.0
                    ],
                    [
                        492.0,
                        303.0
                    ],
                    [
                        493.0,
                        298.0
                    ],
                    [
                        495.0,
                        305.0
                    ],
                    [
                        498.0,
                        309.0
                    ],
                    [
                        501.0,
                        312.0
                    ],
                    [
                        501.0,
                        314.0
                    ]
                ],
                "interior": []
            }
        }
    ],
    "size": {
        "height": 644,
        "width": 903
    }
}